pathomap/Bodymap.py
pathomap/Gene.py
pathomap/Organ.py
pathomap/__init__.py
pathomap/misc.py
pathomap/data/.DS_Store
pathomap/data/abstract_gene_weight_matrix.csv
pathomap/data/expression_value.csv
pathomap/data/gene_tissue_similarity.csv
pathomap-1.0.0.dist-info/LICENSE
pathomap-1.0.0.dist-info/METADATA
pathomap-1.0.0.dist-info/WHEEL
pathomap-1.0.0.dist-info/top_level.txt
pathomap-1.0.0.dist-info/RECORD
