Metadata-Version: 2.1
Name: pathomap
Version: 1.0.0
Summary: The Pathomap package
Home-page: https://github.com/Br34th7aking/Pathomap
Author: Abhijit Raj
Author-email: abhijit18231@iiitd.ac.in
License: UNKNOWN
Platform: UNKNOWN
Classifier: Programming Language :: Python :: 3
Classifier: License :: OSI Approved :: MIT License
Classifier: Operating System :: OS Independent
Requires-Python: >=3.6
Requires-Dist: pandas
